{"type":"FeatureCollection","features":[{"type":"Feature","geometry":{"type":"Point","coordinates":[31.235833333,30.044444444]},"properties":{"name":"Cairo","population":9606916}},{"type":"Feature","geometry":{"type":"Point","coordinates":[31.235833333,30.044444444]},"properties":{"name":"Cairo","population":9606916}},{"type":"Feature","geometry":{"type":"Point","coordinates":[31.235833333,30.044444444]},"properties":{"name":"Cairo","population":9606916}},{"type":"Feature","geometry":{"type":"Point","coordinates":[31.235833333,30.044444444]},"properties":{"name":"Cairo","population":9606916}},{"type":"Feature","geometry":{"type":"Point","coordinates":[31.235833333,30.044444444]},"properties":{"name":"Cairo","population":9606916}},{"type":"Feature","geometry":{"type":"Point","coordinates":[31.235833333,30.044444444]},"properties":{"name":"Cairo","population":9606916}},{"type":"Feature","geometry":{"type":"Point","coordinates":[31.235833333,30.044444444]},"properties":{"name":"Cairo","population":9606916}},{"type":"Feature","geometry":{"type":"Point","coordinates":[31.235833333,30.044444444]},"properties":{"name":"Cairo","population":9606916}},{"type":"Feature","geometry":{"type":"Point","coordinates":[31.235833333,30.044444444]},"properties":{"name":"Cairo","population":9606916}},{"type":"Feature","geometry":{"type":"Point","coordinates":[31.235833333,30.044444444]},"properties":{"name":"Cairo","population":9606916}}]}