{"type":"FeatureCollection","features":[{"type":"Feature","geometry":{"type":"Point","coordinates":[-58.3719,-34.6083]},"properties":{"name":"Greater Buenos Aires","population":13985794}},{"type":"Feature","geometry":{"type":"Point","coordinates":[-58.3719,-34.6083]},"properties":{"name":"Greater Buenos Aires","population":13985794}},{"type":"Feature","geometry":{"type":"Point","coordinates":[-58.3719,-34.6083]},"properties":{"name":"Greater Buenos Aires","population":13985794}},{"type":"Feature","geometry":{"type":"Point","coordinates":[-58.3719,-34.6083]},"properties":{"name":"Greater Buenos Aires","population":13985794}},{"type":"Feature","geometry":{"type":"Point","coordinates":[-58.3719,-34.6083]},"properties":{"name":"Greater Buenos Aires","population":13985794}},{"type":"Feature","geometry":{"type":"Point","coordinates":[-58.3719,-34.6083]},"properties":{"name":"Greater Buenos Aires","population":13985794}},{"type":"Feature","geometry":{"type":"Point","coordinates":[-58.381944444,-34.599722222]},"properties":{"name":"Buenos Aires","population":3121707}},{"type":"Feature","geometry":{"type":"Point","coordinates":[-58.381944444,-34.599722222]},"properties":{"name":"Buenos Aires","population":3121707}},{"type":"Feature","geometry":{"type":"Point","coordinates":[-58.381944444,-34.599722222]},"properties":{"name":"Buenos Aires","population":3121707}},{"type":"Feature","geometry":{"type":"Point","coordinates":[-58.381944444,-34.599722222]},"properties":{"name":"Buenos Aires","population":3121707}}]}