{"type":"FeatureCollection","features":[{"type":"Feature","geometry":{"type":"Point","coordinates":[106.506944444,29.55]},"properties":{"name":"Chongqing","population":32054159}},{"type":"Feature","geometry":{"type":"Point","coordinates":[106.506944444,29.55]},"properties":{"name":"Chongqing","population":32054159}},{"type":"Feature","geometry":{"type":"Point","coordinates":[106.506944444,29.55]},"properties":{"name":"Chongqing","population":32054159}},{"type":"Feature","geometry":{"type":"Point","coordinates":[106.506944444,29.55]},"properties":{"name":"Chongqing","population":32054159}},{"type":"Feature","geometry":{"type":"Point","coordinates":[106.506944444,29.55]},"properties":{"name":"Chongqing","population":32054159}},{"type":"Feature","geometry":{"type":"Point","coordinates":[106.506944444,29.55]},"properties":{"name":"Chongqing","population":32054159}},{"type":"Feature","geometry":{"type":"Point","coordinates":[106.506944444,29.55]},"properties":{"name":"Chongqing","population":32054159}},{"type":"Feature","geometry":{"type":"Point","coordinates":[106.506944444,29.55]},"properties":{"name":"Chongqing","population":32054159}},{"type":"Feature","geometry":{"type":"Point","coordinates":[106.506944444,29.55]},"properties":{"name":"Chongqing","population":32054159}},{"type":"Feature","geometry":{"type":"Point","coordinates":[106.506944444,29.55]},"properties":{"name":"Chongqing","population":32054159}}]}